pandacolumns/PandaDrop.py
pandacolumns/__init__.py
pandacolumns/dynamic.py
pandacolumns/pandacolumns.py
pandacolumns-0.2.3.dist-info/METADATA
pandacolumns-0.2.3.dist-info/WHEEL
pandacolumns-0.2.3.dist-info/top_level.txt
pandacolumns-0.2.3.dist-info/RECORD
