Metadata-Version: 2.1
Name: pandacolumns
Version: 0.2.3
Summary: Easily work with the pandas dataframes with an interactive interface
Author: Asif Syed
License: MIT
Requires-Dist: pandas
Requires-Dist: ipywidgets
Requires-Dist: IPython
